git2gpt/__init__.py
git2gpt/core.py
git2gpt/main.py
git2gpt/models.py
git2gpt/version.py
git2gpt-0.1.7.dist-info/LICENSE
git2gpt-0.1.7.dist-info/METADATA
git2gpt-0.1.7.dist-info/WHEEL
git2gpt-0.1.7.dist-info/entry_points.txt
git2gpt-0.1.7.dist-info/top_level.txt
git2gpt-0.1.7.dist-info/RECORD
