Metadata-Version: 2.1
Name: git2gpt
Version: 0.1.7
Summary: UNKNOWN
Home-page: UNKNOWN
License: UNKNOWN
Platform: UNKNOWN
License-File: LICENSE
Requires-Dist: openai (>=0.27.2)
Requires-Dist: python-dotenv
Requires-Dist: tiktoken
